pydoge_redis/__init__.py
pydoge_redis/redis_client.py
PyDoge_redis-0.1.1.dist-info/LICENSE
PyDoge_redis-0.1.1.dist-info/METADATA
PyDoge_redis-0.1.1.dist-info/WHEEL
PyDoge_redis-0.1.1.dist-info/top_level.txt
PyDoge_redis-0.1.1.dist-info/RECORD
